gridwayai/__init__.py
gridwayai/client.py
gridwayai/exceptions.py
gridwayai-0.1.11.dist-info/licenses/LICENSE
gridwayai-0.1.11.dist-info/METADATA
gridwayai-0.1.11.dist-info/WHEEL
gridwayai-0.1.11.dist-info/top_level.txt
gridwayai-0.1.11.dist-info/RECORD
