Metadata-Version: 2.4
Name: gridwayai
Version: 0.1.11
Summary: SDK for accessing GridwayAI endpoints
Author-email: Rob <rob@gridwayai.com>
License-Expression: MIT
Project-URL: Homepage, https://github.com/gridwayai/gridwayai-sdk
Requires-Python: >=3.8
License-File: LICENSE
Requires-Dist: requests
Dynamic: license-file
